AUTHORS
CHANGES
LICENSE
MANIFEST.in
README
setup.py
WFront.egg-info/PKG-INFO
WFront.egg-info/SOURCES.txt
WFront.egg-info/dependency_links.txt
WFront.egg-info/requires.txt
WFront.egg-info/top_level.txt
WFront.egg-info/zip-safe
docs/html/examples.html
docs/html/filter.html
docs/html/genindex.html
docs/html/index.html
docs/html/mappings.html
docs/html/modindex.html
docs/html/objects.inv
docs/html/overview.html
docs/html/routing.html
docs/html/search.html
docs/html/searchindex.js
docs/html/_sources/examples.txt
docs/html/_sources/filter.txt
docs/html/_sources/index.txt
docs/html/_sources/mappings.txt
docs/html/_sources/overview.txt
docs/html/_sources/routing.txt
docs/html/_static/contents.png
docs/html/_static/default.css
docs/html/_static/doctools.js
docs/html/_static/file.png
docs/html/_static/jquery.js
docs/html/_static/minus.png
docs/html/_static/navigation.png
docs/html/_static/plus.png
docs/html/_static/pygments.css
docs/html/_static/rightsidebar.css
docs/html/_static/searchtools.js
docs/html/_static/sphinxdoc.css
docs/html/_static/stickysidebar.css
docs/html/_static/traditional.css
docs/source/Makefile
docs/source/conf.py
docs/source/examples.rst
docs/source/filter.rst
docs/source/index.rst
docs/source/mappings.rst
docs/source/overview.rst
docs/source/routing.rst
docs/source/_lib/__init__.py
docs/source/_lib/__init__.pyc
docs/source/_lib/examples.py
docs/source/_lib/examples.pyc
docs/source/_lib/funcsig.py
docs/source/_lib/funcsig.pyc
docs/text/examples.txt
docs/text/filter.txt
docs/text/index.txt
docs/text/mappings.txt
docs/text/overview.txt
docs/text/routing.txt
tests/__init__.py
tests/test_cleanups.py
tests/test_examples.py
tests/test_internal.py
tests/test_matcher.py
wfront/__init__.py
wfront/_internal.py
wfront/base.py
wfront/multiserver.py
wfront/resolvers.py
wfront/rewriter.py