Metadata-Version: 1.0
Name: WFront
Version: 0.4
Summary: A WSGI front-door dispatcher.
Home-page: http://discorporate.us/projects/WFront/
Author: Jason Kirtland
Author-email: jek@discorporate.us
License: MIT License
Keywords: wsgi web http vhost virtualhost proxy mod_proxy dispatcher
Platform: UNKNOWN
Classifier: Development Status :: 4 - Beta
Classifier: Environment :: Web Environment
Classifier: Intended Audience :: Developers
Classifier: License :: OSI Approved :: MIT License
Classifier: Natural Language :: English
Classifier: Operating System :: OS Independent
Classifier: Programming Language :: Python
Classifier: Programming Language :: Python :: 2.4
Classifier: Programming Language :: Python :: 2.5
Classifier: Programming Language :: Python :: 2.6
Classifier: Topic :: Internet :: WWW/HTTP :: WSGI :: Middleware
Classifier: Topic :: Software Development :: Libraries
